luccpy/__init__.py
luccpy/calc.py
luccpy/calc_deterministic.py
luccpy/geoutils.py
luccpy/transformer.py
luccpy-0.2.3.dist-info/licenses/LICENSE
luccpy-0.2.3.dist-info/METADATA
luccpy-0.2.3.dist-info/WHEEL
luccpy-0.2.3.dist-info/top_level.txt
luccpy-0.2.3.dist-info/RECORD
